invctrl/__init__.py
invctrl/main.py
invctrl/models/__init__.py
invctrl/models/delivery_order.py
invctrl/models/request_order.py
invctrl/models/stock.py
invctrl/routes/__init__.py
invctrl/routes/request_order.py
invctrl/utils/__init__.py
invctrl/utils/file_db.py
invctrl-0.2.0.dist-info/licenses/LICENSE
invctrl-0.2.0.dist-info/METADATA
invctrl-0.2.0.dist-info/WHEEL
invctrl-0.2.0.dist-info/entry_points.txt
invctrl-0.2.0.dist-info/top_level.txt
invctrl-0.2.0.dist-info/RECORD
