Metadata-Version: 2.4
Name: invctrl
Version: 0.2.0
Summary: Inventory Control
Author: Indra Setiawan
Author-email: Indra Setiawan <portgash.the.ace@gmail.com>
License: MIT
Project-URL: Homepage, https://github.com/gand0r/invctrl
Project-URL: Issues, https://github.com/gand0r/invctrl/issues
Classifier: Programming Language :: Python :: 3
Classifier: Framework :: FastAPI
Classifier: Operating System :: OS Independent
Requires-Python: >=3.7
License-File: LICENSE
Requires-Dist: fastapi
Requires-Dist: uvicorn[standard]
Requires-Dist: tinydb
Requires-Dist: jinja2
Requires-Dist: asgiref==3.8.1
Requires-Dist: python-multipart==0.0.20
Requires-Dist: sqlparse==0.5.0
Requires-Dist: telnetlib3==2.0.4
Requires-Dist: tzdata==2024.1
Dynamic: author
Dynamic: license-file
Dynamic: requires-python
